nicemail/__init__.py
nicemail-0.1.0.dist-info/licenses/LICENSE
send/__init__.py
send/cli.py
send/client.py
send/logging.py
send/auth/__init__.py
send/auth/google_device_code.py
send/auth/msal_device_code.py
send/common/config.py
send/credentials/__init__.py
send/credentials/models.py
send/credentials/paths.py
send/credentials/store.py
send/message/__init__.py
send/message/builder.py
send/message/models.py
send/runtime/__init__.py
send/runtime/context.py
send/runtime/env.py
send/runtime/paths.py
send/transport/__init__.py
send/transport/dry_run_transport.py
send/transport/google_transport.py
send/transport/ms_graph_transport.py
send/transport/send.py
nicemail-0.1.0.dist-info/METADATA
nicemail-0.1.0.dist-info/WHEEL
nicemail-0.1.0.dist-info/entry_points.txt
nicemail-0.1.0.dist-info/top_level.txt
nicemail-0.1.0.dist-info/RECORD
