Metadata-Version: 2.4
Name: nicemail
Version: 0.1.0
Summary: A simple email package
Author-email: Rajinder Mavi <rajinder@mavi.phd>
License: MIT
Project-URL: Homepage, https://github.com/rajindermavi/nicemail
Project-URL: Issues, https://github.com/rajindermavi/nicemail/issues
Classifier: Programming Language :: Python :: 3
Classifier: Operating System :: OS Independent
Requires-Python: >=3.12
License-File: LICENSE
Requires-Dist: cryptography>=46.0.3
Requires-Dist: msal>=1.34.0
Requires-Dist: platformdirs>=4.5.1
Requires-Dist: requests>=2.32.5
Provides-Extra: dev
Requires-Dist: pytest>=9.0.2; extra == "dev"
Requires-Dist: build; extra == "dev"
Requires-Dist: twine; extra == "dev"
Dynamic: license-file
